__init__.py
main.py
trgelectro_cicd_test-0.1.1.dist-info/METADATA
trgelectro_cicd_test-0.1.1.dist-info/WHEEL
trgelectro_cicd_test-0.1.1.dist-info/top_level.txt
trgelectro_cicd_test-0.1.1.dist-info/RECORD
