Metadata-Version: 2.4
Name: trgelectro-cicd-test
Version: 0.1.1
Summary: A minimal hello world Python application
Author-email: trgelectro <trgelectro@email.com>
